textutils/__init__.py
textutils/utils.py
eztextutils-0.1.0.dist-info/METADATA
eztextutils-0.1.0.dist-info/WHEEL
eztextutils-0.1.0.dist-info/top_level.txt
eztextutils-0.1.0.dist-info/RECORD
